pacchettodig/__init__.py
pacchettodig/module1.py
pacchettodig/module2.py
pacchettoDiG-0.0.3.dist-info/LICENSE
pacchettoDiG-0.0.3.dist-info/METADATA
pacchettoDiG-0.0.3.dist-info/WHEEL
pacchettoDiG-0.0.3.dist-info/top_level.txt
pacchettoDiG-0.0.3.dist-info/RECORD
