Metadata-Version: 2.1
Name: pacchettoDiG
Version: 0.0.3
Summary: A comprehensive useless package.
Home-page: UNKNOWN
Author: Gabriele Pittarello
License: BSD 3-Clause
Project-URL: Source Code, https://github.com/GEM-analytics
Platform: UNKNOWN
Classifier: Development Status :: 3 - Alpha
Classifier: License :: OSI Approved :: BSD License
Classifier: Programming Language :: Python
Classifier: Operating System :: Unix
Classifier: Operating System :: MacOS :: MacOS X
Classifier: Operating System :: Microsoft :: Windows
License-File: LICENSE
Requires-Dist: twiggy
Requires-Dist: numpy (>=1.21.4)
Requires-Dist: matplotlib (>=3.5.0)
Requires-Dist: scipy (>=1.7.2)
